django_healthwatch-0.1.0.dist-info/licenses/LICENSE
healthcheck_plus/__init__.py
healthcheck_plus/admin.py
healthcheck_plus/apps.py
healthcheck_plus/models.py
healthcheck_plus/registry.py
healthcheck_plus/settings.py
healthcheck_plus/tasks.py
healthcheck_plus/utils.py
healthcheck_plus/alerts/__init__.py
healthcheck_plus/alerts/base.py
healthcheck_plus/alerts/email.py
healthcheck_plus/alerts/manager.py
healthcheck_plus/alerts/sms.py
healthcheck_plus/checks/__init__.py
healthcheck_plus/checks/base.py
healthcheck_plus/checks/cache_check.py
healthcheck_plus/checks/db_check.py
healthcheck_plus/checks/storage_check.py
healthcheck_plus/management/__init__.py
healthcheck_plus/management/commands/__init__.py
healthcheck_plus/management/commands/health_check.py
healthcheck_plus/tests/__init__.py
healthcheck_plus/tests/test_checks.py
django_healthwatch-0.1.0.dist-info/METADATA
django_healthwatch-0.1.0.dist-info/WHEEL
django_healthwatch-0.1.0.dist-info/top_level.txt
django_healthwatch-0.1.0.dist-info/RECORD
